sefrone_api_e2e/__init__.py
sefrone_api_e2e/api_e2e_manager.py
sefrone_api_e2e-1.0.2.dist-info/METADATA
sefrone_api_e2e-1.0.2.dist-info/WHEEL
sefrone_api_e2e-1.0.2.dist-info/top_level.txt
sefrone_api_e2e-1.0.2.dist-info/RECORD
