Metadata-Version: 2.1
Name: sefrone-api-e2e
Version: 1.0.2
Summary: A Python package to provide e2e testing helpers for sefrone API projects
Home-page: https://bitbucket.org/sefrone/sefrone_pypi
Author: Sefrone
Author-email: contact@sefrone.com
License: UNKNOWN
Platform: UNKNOWN
Classifier: Programming Language :: Python :: 3
Classifier: License :: Other/Proprietary License
Classifier: Operating System :: OS Independent
Requires-Python: >=3.7
Requires-Dist: PyYAML>=6.0.1
Requires-Dist: requests
